{
  "lawyers": [
    {
      "id": 1,
      "name": "Juan Carlos Perez Rodriguez",
      "yearsOfExperience": 10,
      "specialization": "Medical Malpractice Law",
      "urlToImage": "https://www.narcity.com/media-library/image.jpg?id=25902742&width=1245&height=700&coordinates=0%2C5%2C0%2C5",
      "casesWon": 50,
      "price": "$300/hour",
      "email": "juan.carlos@example.com",
      "phoneNumber": "+1234567890"
    },
    {
      "id": 2,
      "name": "Maria Luisa Gonzales Fernandez",
      "yearsOfExperience": 15,
      "specialization": "Healthcare Law",
      "urlToImage": "https://kcdefensecounsel.b-cdn.net/wp-content/uploads/2023/03/female-intelligent-law-attorney-lawyers-working-at-2023-03-08-20-54-26-utc-1-scaled.jpg",
      "casesWon": 70,
      "price": "$350/hour",
      "email": "maria.luisa@example.com",
      "phoneNumber": "+1987654321"
    },
    {
      "id": 3,
      "name": "Diego Flores Ramirez",
      "yearsOfExperience": 12,
      "specialization": "Pharmaceutical Law",
      "urlToImage": "https://static.independent.co.uk/s3fs-public/thumbnails/image/2017/03/16/12/saul-goodman.jpg?width=1200",
      "casesWon": 60,
      "price": "$320/hour",
      "email": "diego.flores@example.com",
      "phoneNumber": "+1122334455"
    },
    {
      "id": 4,
      "name": "Fernanda Rojas Torres",
      "yearsOfExperience": 8,
      "specialization": "Public Health Law",
      "urlToImage": "https://api3.talentrocket.de/files/article/backgroundpicture/85752/Foreign%20Lawyer.jpg",
      "casesWon": 40,
      "price": "$280/hour",
      "email": "fernanda.rojas@example.com",
      "phoneNumber": "+9988776655"
    },
    {
      "id": 5,
      "name": "Santiago Chavez Cruz",
      "yearsOfExperience": 20,
      "specialization": "Medical Ethics Law",
      "urlToImage": "https://imageio.forbes.com/specials-images/imageserve/640e3166569159b2e37aa269/African-American-lawyer-fighting-for-justice-/960x0.jpg?format=jpg&width=960",
      "casesWon": 50,
      "price": "$300/hour",
      "email": "santiago.chavez@example.com",
      "phoneNumber": "+9988776655"
    },
    {
      "id": 6,
      "name": "Valeria Medina Alvarado",
      "yearsOfExperience": 7,
      "specialization": "Mental Health Law",
      "urlToImage": "https://blog.lemontech.com/wp-content/uploads/2021/07/perfil-profesional-de-un-abogado.jpg",
      "casesWon": 24,
      "price": "$190/hour",
      "email": "valeria.medina@example.com",
      "phoneNumber": "+9988776655"
    },
    {
      "id": 7,
      "name": "Carlos Alberto Vargas Gutierrez",
      "yearsOfExperience": 18,
      "specialization": "Health Insurance Law",
      "urlToImage": "https://img.freepik.com/fotos-premium/hombre-asiatico-indio-vestido-estilo-esta-pie-calle-dia-lleva-traje-3-piezas-zapatos-moda-bolsillo-cuadrado-pendientes-sostiene-bolsa-gimnasia-mano_396607-57297.jpg?w=900",
      "casesWon": 40,
      "price": "$280/hour",
      "email": "carlos.vargas@example.com",
      "phoneNumber": "+9988776655"
    },
    {
      "id": 8,
      "name": "Luz Marina Velasquez Diaz",
      "yearsOfExperience": 11,
      "specialization": "Medical Device Law",
      "urlToImage": "https://static.vecteezy.com/system/resources/previews/007/359/462/non_2x/young-beautiful-asian-woman-lawyer-who-working-in-the-office-tlaking-on-a-smart-phone-with-client-free-photo.JPG",
      "casesWon": 10,
      "price": "$100/hour",
      "email": "luz.marina@example.com",
      "phoneNumber": "+9988776655"
    },
    {
      "id": 9,
      "name": "Gonzalo Paredes Silva",
      "yearsOfExperience": 14,
      "specialization": "Bioethics Law",
      "urlToImage": "https://preview.redd.it/zsaqp5bjshh71.jpg?auto=webp&s=2e1d7cede9b57081ff249fbb08153630d804baaa",
      "casesWon": 150,
      "price": "$500/hour",
      "email": "gonzalo.paredes@example.com",
      "phoneNumber": "+9988776655"
    },
    {
      "id": 10,
      "name": "Ana Sofia Castillo Mendoza",
      "yearsOfExperience": 9,
      "specialization": "Health Regulation Law",
      "urlToImage": "https://www.google.com/url?sa=i&url=https%3A%2F%2Fwww.twitchmetrics.net%2Fc%2F261778616-zekagamerss%2Fclips%3Fpage%3D3&psig=AOvVaw0pdlqLChtN1E_GRDjTg4Sr&ust=1718765355735000&source=images&cd=vfe&opi=89978449&ved=0CA8QjRxqFwoTCIiJooiS5IYDFQAAAAAdAAAAABBR",
      "casesWon": 22,
      "price": "$254/hour",
      "email": "ana.sofia@example.com",
      "phoneNumber": "+9988776655"
    }
  ]
  "educational-resources": [
    {
    "id": 1,
    "title": "Ethics and Advocacy in Medicine",
    "description": "This resource offers an overview of the intersection between medical ethics and advocacy. It covers topics such as confidentiality, informed consent, and ethical decision-making in patient care. It includes practical cases to illustrate how medical professionals can advocate for their patients in ethically challenging situations.",
    "authorsId": 11,
    "educationalResourceType": "Online Course"
  },
  {
    "id": 2,
    "title": "Advocacy Manual for Healthcare Professionals",
    "description": "This manual provides a comprehensive guide on how doctors can actively play a role in advocating for their patients' rights. It includes strategies for patient advocacy in clinical and administrative settings, as well as in public health policy.",
    "authorsId": 12,
    "educationalResourceType": "Manual"
  },
  {
    "id": 3,
    "title": "Advocacy Workshop in Medicine: Practical Skills",
    "description": "This interactive workshop is designed for doctors and medical students, focusing on developing practical advocacy skills in the medical environment. Participants will learn effective communication techniques, negotiation, and leadership to advocate for their patients effectively.",
    "authorsId": 13,
    "educationalResourceType": "In-person/Virtual Workshop"
  },
  {
    "id": 4,
    "title": "Advocacy and Legislation in Medicine",
    "description": "This resource explores the relationship between medicine and legislation, including patients' rights, regulation of medical practice, and the role of healthcare professionals in creating and modifying health policies. It provides case studies and analysis of relevant laws.",
    "authorsId": 14,
    "educationalResourceType": "Textbook"
  },
  {
    "id": 5,
    "title": "Medical Advocacy Webinar Series",
    "description": "A series of webinars addressing various aspects of advocacy in medicine, such as representing vulnerable patients, the impact of advocacy on health policy, and best practices for advocacy in healthcare settings. Includes expert presentations and Q&A sessions.",
    "authorsId": 15,
    "educationalResourceType": "Webinars"
  }
  ]
}
